timeflux_upsidedownlabs/__init__.py
timeflux_upsidedownlabs/nodes/__init__.py
timeflux_upsidedownlabs/nodes/driver.py
timeflux_upsidedownlabs-0.1.4.dist-info/LICENSE
timeflux_upsidedownlabs-0.1.4.dist-info/METADATA
timeflux_upsidedownlabs-0.1.4.dist-info/WHEEL
timeflux_upsidedownlabs-0.1.4.dist-info/top_level.txt
timeflux_upsidedownlabs-0.1.4.dist-info/RECORD
